setup.py
pykarmasubreddit/__init__.py
pykarmasubreddit.egg-info/PKG-INFO
pykarmasubreddit.egg-info/SOURCES.txt
pykarmasubreddit.egg-info/dependency_links.txt
pykarmasubreddit.egg-info/requires.txt
pykarmasubreddit.egg-info/top_level.txt