Metadata-Version: 1.0
Name: pykarmasubreddit
Version: 1.2
Summary: A python API for Karma Decay
Home-page: https://github.com/Aculisme/pykarma
Author: Aculisme
Author-email: luca.mehl@gmail.com
License: MIT
Platform: UNKNOWN
